Workbook
Name ColorList: 'Code Lists'!$G$2:INDEX('Code Lists'!$G:$G,COUNTA('Code Lists'!$G:$G))
Name FabricList: 'Code Lists'!$D$2:INDEX('Code Lists'!$D:$D,COUNTA('Code Lists'!$D:$D))
Name GarmentTypeList: 'Code Lists'!$A$2:INDEX('Code Lists'!$A:$A,COUNTA('Code Lists'!$A:$A))
Name PatternList: 'Code Lists'!$N$2:INDEX('Code Lists'!$N:$N,COUNTA('Code Lists'!$N:$N))
Name SizeList: 'Code Lists'!$J$2:INDEX('Code Lists'!$J:$J,COUNTA('Code Lists'!$J:$J))

Sheet SKU Master
A1: Design No. | B1: Garment Type | C1: Type Code | D1: Set Type | E1: Fabric | F1: Fabric Code | G1: Color | H1: Color Code | I1: Size | J1: Year | K1: Pattern | L1: Neck Type | M1: Short Important Description | N1: Pocket | O1: Stock | P1: HSN/SAC Code | Q1: GST % | R1: Model Number | S1: Sellable SKU | T1: Product Name | U1: MRP | V1: Selling Price | W1: Cost | X1: Photoshoot Status | Y1: Website Status | Z1: 01 Front | AA1: 02 Side | AB1: 03 Back | AC1: 04 Candid | AD1: 05 Walking | AE1: 06 Seated | AF1: Fabric Close-up | AG1: Detail | AH1: Reference 01 | AI1: Notes
A2: 1 | B2: Co-ord Set | C2: =IFERROR(VLOOKUP(B2,'Code Lists'!$A:$B,2,FALSE),"") -> CRD | D2: 2PC | E2: Satin | F2: =IFERROR(VLOOKUP(E2,'Code Lists'!$D:$E,2,FALSE),"") -> STN | G2: Brown | H2: =IFERROR(VLOOKUP(G2,'Code Lists'!$G:$H,2,FALSE),"") -> BRN | I2: M,L,XL | J2: 2026 | K2: Plain | L2: Mandarin Collar | M2: Relaxed-fit satin co-ord set featuring an asymmetric kaftan-style button-down top, wide batwing sleeves with lace-trim detailing, and matching wide-leg pants. | N2: Yes | O2: 3 | P2: 998822 | Q2: =IF(VedAarnaSKUMaster[[#This Row],[HSN/SAC Code]]=998822,5%,IF(VedAarnaSKUMaster[[#This Row],[HSN/SAC Code]]=998391,18%,IF(VedAarnaSKUMaster[[#This Row],[HSN/SAC Code]]=998723,5%,""))) -> 0.05 | R2: =IF(OR(A2="",C2="",H2="",J2=""),"","VS-"&C2&IF(D2<>"","-"&D2,"")&"-"&TEXT(A2,"0000")&"-"&H2&"-"&RIGHT(TEXT(J2,"0000"),2)) -> VS-CRD-2PC-0001-BRN-26 | S2: =IF(OR(A2="",C2="",F2="",H2="",I2="",J2=""),"","VS-"&C2&IF(D2<>"","-"&D2,"")&"-"&TEXT(A2,"0000")&"-"&F2&"-"&H2&"-"&I2&"-"&RIGHT(TEXT(J2,"0000"),2)) -> VS-CRD-2PC-0001-STN-BRN-M,L,XL-26 | T2: Chocolate Brown Satin Co-ord Set | U2: =IF(OR(VedAarnaSKUMaster[[#This Row],[Selling Price]]="",VedAarnaSKUMaster[[#This Row],[Selling Price]]=0),"",CEILING(VedAarnaSKUMaster[[#This Row],[Selling Price]]/(1-20%),100)-1) -> 3799 | V2: =ROUND(W2/(1-50%),-2) -> 3000 | W2: 1500 | X2: Complete | Y2: Live | Z2: =IF($R2="","",$R2&"-01-FR.png") -> VS-CRD-2PC-0001-BRN-26-01-FR.png | AA2: =IF($R2="","",$R2&"-02-SD.png") -> VS-CRD-2PC-0001-BRN-26-02-SD.png | AB2: =IF($R2="","",$R2&"-03-BK.png") -> VS-CRD-2PC-0001-BRN-26-03-BK.png | AC2: =IF($R2="","",$R2&"-04-CD.png") -> VS-CRD-2PC-0001-BRN-26-04-CD.png | AD2: =IF($R2="","",$R2&"-05-WK.png") -> VS-CRD-2PC-0001-BRN-26-05-WK.png | AE2: =IF($R2="","",$R2&"-06-ST.png") -> VS-CRD-2PC-0001-BRN-26-06-ST.png | AF2: =IF($R2="","",$R2&"-FB.png") -> VS-CRD-2PC-0001-BRN-26-FB.png | AG2: =IF($R2="","",$R2&"-DT.png") -> VS-CRD-2PC-0001-BRN-26-DT.png | AH2: =IF($R2="","",$R2&"-REF-01.png") -> VS-CRD-2PC-0001-BRN-26-REF-01.png
A3: 2 | B3: Three Piece Set | C3: =IFERROR(VLOOKUP(B3,'Code Lists'!$A:$B,2,FALSE),"") -> THS | D3: 3PC | E3: Art Silk | F3: =IFERROR(VLOOKUP(E3,'Code Lists'!$D:$E,2,FALSE),"") -> ASL | G3: Multicolor | H3: =IFERROR(VLOOKUP(G3,'Code Lists'!$G:$H,2,FALSE),"") -> MLT | I3: M,L,XL | J3: 2026 | K3: Printed | L3: V-Neck | M3: Contemporary three-piece co-ord set featuring a solid emerald green V-neck inner top, long open-front printed jacket, and matching wide-leg printed pants. | N3: No | O3: 3 | P3: 998822 | Q3: =IF(VedAarnaSKUMaster[[#This Row],[HSN/SAC Code]]=998822,5%,IF(VedAarnaSKUMaster[[#This Row],[HSN/SAC Code]]=998391,18%,IF(VedAarnaSKUMaster[[#This Row],[HSN/SAC Code]]=998723,5%,""))) -> 0.05 | R3: =IF(OR(A3="",C3="",H3="",J3=""),"","VS-"&C3&IF(D3<>"","-"&D3,"")&"-"&TEXT(A3,"0000")&"-"&H3&"-"&RIGHT(TEXT(J3,"0000"),2)) -> VS-THS-3PC-0002-MLT-26 | S3: =IF(OR(A3="",C3="",F3="",H3="",I3="",J3=""),"","VS-"&C3&IF(D3<>"","-"&D3,"")&"-"&TEXT(A3,"0000")&"-"&F3&"-"&H3&"-"&I3&"-"&RIGHT(TEXT(J3,"0000"),2)) -> VS-THS-3PC-0002-ASL-MLT-M,L,XL-26 | T3: Multicolor Geometric Print Three-Piece Co-ord Set | U3: =IF(OR(VedAarnaSKUMaster[[#This Row],[Selling Price]]="",VedAarnaSKUMaster[[#This Row],[Selling Price]]=0),"",CEILING(VedAarnaSKUMaster[[#This Row],[Selling Price]]/(1-20%),100)-1) -> 4999 | V3: =ROUND(W3/(1-50%),-2) -> 4000 | W3: 2000 | X3: Complete | Y3: Live | Z3: =IF($R3="","",$R3&"-01-FR.png") -> VS-THS-3PC-0002-MLT-26-01-FR.png | AA3: =IF($R3="","",$R3&"-02-SD.png") -> VS-THS-3PC-0002-MLT-26-02-SD.png | AB3: =IF($R3="","",$R3&"-03-BK.png") -> VS-THS-3PC-0002-MLT-26-03-BK.png | AC3: =IF($R3="","",$R3&"-04-CD.png") -> VS-THS-3PC-0002-MLT-26-04-CD.png | AD3: =IF($R3="","",$R3&"-05-WK.png") -> VS-THS-3PC-0002-MLT-26-05-WK.png | AE3: =IF($R3="","",$R3&"-06-ST.png") -> VS-THS-3PC-0002-MLT-26-06-ST.png | AF3: =IF($R3="","",$R3&"-FB.png") -> VS-THS-3PC-0002-MLT-26-FB.png | AG3: =IF($R3="","",$R3&"-DT.png") -> VS-THS-3PC-0002-MLT-26-DT.png | AH3: =IF($R3="","",$R3&"-REF-01.png") -> VS-THS-3PC-0002-MLT-26-REF-01.png
A4: 3 | B4: Suit Set | C4: =IFERROR(VLOOKUP(B4,'Code Lists'!$A:$B,2,FALSE),"") -> SUT | D4: 3PC | E4: Pure Cotton | F4: =IFERROR(VLOOKUP(E4,'Code Lists'!$D:$E,2,FALSE),"") -> PCT | G4: Deep Wine | H4: =IFERROR(VLOOKUP(G4,'Code Lists'!$G:$H,2,FALSE),"") -> DPW | I4: M,L | J4: 2026 | K4: Bandhani | L4: V-Neck | M4: Elegant Bandhani-inspired three-piece set featuring a relaxed long V-neck kurta with contrast trim, matching wide-leg pants and coordinated dupatta. | N4: No | O4: 2 | P4: 998822 | Q4: =IF(VedAarnaSKUMaster[[#This Row],[HSN/SAC Code]]=998822,5%,IF(VedAarnaSKUMaster[[#This Row],[HSN/SAC Code]]=998391,18%,IF(VedAarnaSKUMaster[[#This Row],[HSN/SAC Code]]=998723,5%,""))) -> 0.05 | R4: =IF(OR(A4="",C4="",H4="",J4=""),"","VS-"&C4&IF(D4<>"","-"&D4,"")&"-"&TEXT(A4,"0000")&"-"&H4&"-"&RIGHT(TEXT(J4,"0000"),2)) -> VS-SUT-3PC-0003-DPW-26 | S4: =IF(OR(A4="",C4="",F4="",H4="",I4="",J4=""),"","VS-"&C4&IF(D4<>"","-"&D4,"")&"-"&TEXT(A4,"0000")&"-"&F4&"-"&H4&"-"&I4&"-"&RIGHT(TEXT(J4,"0000"),2)) -> VS-SUT-3PC-0003-PCT-DPW-M,L-26 | T4: Wine Bandhani Three-Piece Kurta Set | U4: =IF(OR(VedAarnaSKUMaster[[#This Row],[Selling Price]]="",VedAarnaSKUMaster[[#This Row],[Selling Price]]=0),"",CEILING(VedAarnaSKUMaster[[#This Row],[Selling Price]]/(1-20%),100)-1) -> 3799 | V4: =ROUND(W4/(1-50%),-2) -> 3000 | W4: 1500 | X4: Complete | Y4: Live | Z4: =IF($R4="","",$R4&"-01-FR.png") -> VS-SUT-3PC-0003-DPW-26-01-FR.png | AA4: =IF($R4="","",$R4&"-02-SD.png") -> VS-SUT-3PC-0003-DPW-26-02-SD.png | AB4: =IF($R4="","",$R4&"-03-BK.png") -> VS-SUT-3PC-0003-DPW-26-03-BK.png | AC4: =IF($R4="","",$R4&"-04-CD.png") -> VS-SUT-3PC-0003-DPW-26-04-CD.png | AD4: =IF($R4="","",$R4&"-05-WK.png") -> VS-SUT-3PC-0003-DPW-26-05-WK.png | AE4: =IF($R4="","",$R4&"-06-ST.png") -> VS-SUT-3PC-0003-DPW-26-06-ST.png | AF4: =IF($R4="","",$R4&"-FB.png") -> VS-SUT-3PC-0003-DPW-26-FB.png | AG4: =IF($R4="","",$R4&"-DT.png") -> VS-SUT-3PC-0003-DPW-26-DT.png | AH4: =IF($R4="","",$R4&"-REF-01.png") -> VS-SUT-3PC-0003-DPW-26-REF-01.png
A5: 4 | B5: Suit Set | C5: =IFERROR(VLOOKUP(B5,'Code Lists'!$A:$B,2,FALSE),"") -> SUT | D5: 3PC | E5: Mix Cotton | F5: =IFERROR(VLOOKUP(E5,'Code Lists'!$D:$E,2,FALSE),"") -> MIC | G5: Ivory | H5: =IFERROR(VLOOKUP(G5,'Code Lists'!$G:$H,2,FALSE),"") -> IVR | I5: M,L,XL | J5: 2026 | K5: Solid with Embroidered Motifs | L5: Round Neck | M5: Elegant pista green three-piece kurta set featuring delicate all-over embroidery, an embellished neckline and decorative lace border, paired with straight pants and a lightweight ivory embroidered dupatta. | N5: No | O5: 3 | P5: 998822 | Q5: =IF(VedAarnaSKUMaster[[#This Row],[HSN/SAC Code]]=998822,5%,IF(VedAarnaSKUMaster[[#This Row],[HSN/SAC Code]]=998391,18%,IF(VedAarnaSKUMaster[[#This Row],[HSN/SAC Code]]=998723,5%,""))) -> 0.05 | R5: =IF(OR(A5="",C5="",H5="",J5=""),"","VS-"&C5&IF(D5<>"","-"&D5,"")&"-"&TEXT(A5,"0000")&"-"&H5&"-"&RIGHT(TEXT(J5,"0000"),2)) -> VS-SUT-3PC-0004-IVR-26 | S5: =IF(OR(A5="",C5="",F5="",H5="",I5="",J5=""),"","VS-"&C5&IF(D5<>"","-"&D5,"")&"-"&TEXT(A5,"0000")&"-"&F5&"-"&H5&"-"&I5&"-"&RIGHT(TEXT(J5,"0000"),2)) -> VS-SUT-3PC-0004-MIC-IVR-M,L,XL-26 | T5: Pista Green Embroidered Three-Piece Kurta Set | U5: =IF(OR(VedAarnaSKUMaster[[#This Row],[Selling Price]]="",VedAarnaSKUMaster[[#This Row],[Selling Price]]=0),"",CEILING(VedAarnaSKUMaster[[#This Row],[Selling Price]]/(1-20%),100)-1) -> 2999 | V5: =ROUND(W5/(1-50%),-2) -> 2400 | W5: 1200 | X5: Complete | Y5: Live | Z5: =IF($R5="","",$R5&"-01-FR.png") -> VS-SUT-3PC-0004-IVR-26-01-FR.png | AA5: =IF($R5="","",$R5&"-02-SD.png") -> VS-SUT-3PC-0004-IVR-26-02-SD.png | AB5: =IF($R5="","",$R5&"-03-BK.png") -> VS-SUT-3PC-0004-IVR-26-03-BK.png | AC5: =IF($R5="","",$R5&"-04-CD.png") -> VS-SUT-3PC-0004-IVR-26-04-CD.png | AD5: =IF($R5="","",$R5&"-05-WK.png") -> VS-SUT-3PC-0004-IVR-26-05-WK.png | AE5: =IF($R5="","",$R5&"-06-ST.png") -> VS-SUT-3PC-0004-IVR-26-06-ST.png | AF5: =IF($R5="","",$R5&"-FB.png") -> VS-SUT-3PC-0004-IVR-26-FB.png | AG5: =IF($R5="","",$R5&"-DT.png") -> VS-SUT-3PC-0004-IVR-26-DT.png | AH5: =IF($R5="","",$R5&"-REF-01.png") -> VS-SUT-3PC-0004-IVR-26-REF-01.png
A6: 5 | B6: Suit Set | C6: =IFERROR(VLOOKUP(B6,'Code Lists'!$A:$B,2,FALSE),"") -> SUT | D6: 3PC | E6: Pure Cotton | F6: =IFERROR(VLOOKUP(E6,'Code Lists'!$D:$E,2,FALSE),"") -> PCT | G6: Grey | H6: =IFERROR(VLOOKUP(G6,'Code Lists'!$G:$H,2,FALSE),"") -> GRY | I6: M,L,XL | J6: 2026 | K6: Bandhani | L6: V-Neck | M6: Contemporary Bandhani three-piece set featuring a charcoal grey flared kurta with bold white geometric tie-dye motifs and lace-trim detailing, paired with deep purple Bandhani pants and a coordinated dual-tone dupatta. | N6: No | O6: 3 | P6: 998822 | Q6: =IF(VedAarnaSKUMaster[[#This Row],[HSN/SAC Code]]=998822,5%,IF(VedAarnaSKUMaster[[#This Row],[HSN/SAC Code]]=998391,18%,IF(VedAarnaSKUMaster[[#This Row],[HSN/SAC Code]]=998723,5%,""))) -> 0.05 | R6: =IF(OR(A6="",C6="",H6="",J6=""),"","VS-"&C6&IF(D6<>"","-"&D6,"")&"-"&TEXT(A6,"0000")&"-"&H6&"-"&RIGHT(TEXT(J6,"0000"),2)) -> VS-SUT-3PC-0005-GRY-26 | S6: =IF(OR(A6="",C6="",F6="",H6="",I6="",J6=""),"","VS-"&C6&IF(D6<>"","-"&D6,"")&"-"&TEXT(A6,"0000")&"-"&F6&"-"&H6&"-"&I6&"-"&RIGHT(TEXT(J6,"0000"),2)) -> VS-SUT-3PC-0005-PCT-GRY-M,L,XL-26 | T6: Charcoal Grey Bandhani Three-Piece Kurta Set | U6: =IF(OR(VedAarnaSKUMaster[[#This Row],[Selling Price]]="",VedAarnaSKUMaster[[#This Row],[Selling Price]]=0),"",CEILING(VedAarnaSKUMaster[[#This Row],[Selling Price]]/(1-20%),100)-1) -> 3799 | V6: =ROUND(W6/(1-50%),-2) -> 3000 | W6: 1500 | X6: Complete | Y6: Live | Z6: =IF($R6="","",$R6&"-01-FR.png") -> VS-SUT-3PC-0005-GRY-26-01-FR.png | AA6: =IF($R6="","",$R6&"-02-SD.png") -> VS-SUT-3PC-0005-GRY-26-02-SD.png | AB6: =IF($R6="","",$R6&"-03-BK.png") -> VS-SUT-3PC-0005-GRY-26-03-BK.png | AC6: =IF($R6="","",$R6&"-04-CD.png") -> VS-SUT-3PC-0005-GRY-26-04-CD.png | AD6: =IF($R6="","",$R6&"-05-WK.png") -> VS-SUT-3PC-0005-GRY-26-05-WK.png | AE6: =IF($R6="","",$R6&"-06-ST.png") -> VS-SUT-3PC-0005-GRY-26-06-ST.png | AF6: =IF($R6="","",$R6&"-FB.png") -> VS-SUT-3PC-0005-GRY-26-FB.png | AG6: =IF($R6="","",$R6&"-DT.png") -> VS-SUT-3PC-0005-GRY-26-DT.png | AH6: =IF($R6="","",$R6&"-REF-01.png") -> VS-SUT-3PC-0005-GRY-26-REF-01.png
A7: 6 | B7: Suit Set | C7: =IFERROR(VLOOKUP(B7,'Code Lists'!$A:$B,2,FALSE),"") -> SUT | D7: 3PC | E7: Rubia Cotton | F7: =IFERROR(VLOOKUP(E7,'Code Lists'!$D:$E,2,FALSE),"") -> RCT | G7: Ivory | H7: =IFERROR(VLOOKUP(G7,'Code Lists'!$G:$H,2,FALSE),"") -> IVR | I7: M,L,XL | J7: 2026 | K7: Paisley / Ethnic Print | L7: Round Neck | M7: Traditional three-piece kurta set featuring an ivory base with all-over red paisley motifs, statement multicolor borders, straight pants and a coordinated red printed dupatta. | N7: No | O7: 3 | P7: 998822 | Q7: =IF(VedAarnaSKUMaster[[#This Row],[HSN/SAC Code]]=998822,5%,IF(VedAarnaSKUMaster[[#This Row],[HSN/SAC Code]]=998391,18%,IF(VedAarnaSKUMaster[[#This Row],[HSN/SAC Code]]=998723,5%,""))) -> 0.05 | R7: =IF(OR(A7="",C7="",H7="",J7=""),"","VS-"&C7&IF(D7<>"","-"&D7,"")&"-"&TEXT(A7,"0000")&"-"&H7&"-"&RIGHT(TEXT(J7,"0000"),2)) -> VS-SUT-3PC-0006-IVR-26 | S7: =IF(OR(A7="",C7="",F7="",H7="",I7="",J7=""),"","VS-"&C7&IF(D7<>"","-"&D7,"")&"-"&TEXT(A7,"0000")&"-"&F7&"-"&H7&"-"&I7&"-"&RIGHT(TEXT(J7,"0000"),2)) -> VS-SUT-3PC-0006-RCT-IVR-M,L,XL-26 | T7: Ivory Red Paisley Print Three-Piece Kurta Set | U7: =IF(OR(VedAarnaSKUMaster[[#This Row],[Selling Price]]="",VedAarnaSKUMaster[[#This Row],[Selling Price]]=0),"",CEILING(VedAarnaSKUMaster[[#This Row],[Selling Price]]/(1-20%),100)-1) -> 3499 | V7: =ROUND(W7/(1-50%),-2) -> 2800 | W7: 1400 | X7: Complete | Y7: Live | Z7: =IF($R7="","",$R7&"-01-FR.png") -> VS-SUT-3PC-0006-IVR-26-01-FR.png | AA7: =IF($R7="","",$R7&"-02-SD.png") -> VS-SUT-3PC-0006-IVR-26-02-SD.png | AB7: =IF($R7="","",$R7&"-03-BK.png") -> VS-SUT-3PC-0006-IVR-26-03-BK.png | AC7: =IF($R7="","",$R7&"-04-CD.png") -> VS-SUT-3PC-0006-IVR-26-04-CD.png | AD7: =IF($R7="","",$R7&"-05-WK.png") -> VS-SUT-3PC-0006-IVR-26-05-WK.png | AE7: =IF($R7="","",$R7&"-06-ST.png") -> VS-SUT-3PC-0006-IVR-26-06-ST.png | AF7: =IF($R7="","",$R7&"-FB.png") -> VS-SUT-3PC-0006-IVR-26-FB.png | AG7: =IF($R7="","",$R7&"-DT.png") -> VS-SUT-3PC-0006-IVR-26-DT.png | AH7: =IF($R7="","",$R7&"-REF-01.png") -> VS-SUT-3PC-0006-IVR-26-REF-01.png
A8: 7 | B8: One Piece | C8: =IFERROR(VLOOKUP(B8,'Code Lists'!$A:$B,2,FALSE),"") -> OPC | D8: 1PC | E8: Chanderi Silk | F8: =IFERROR(VLOOKUP(E8,'Code Lists'!$D:$E,2,FALSE),"") -> CHS | G8: Beige | H8: =IFERROR(VLOOKUP(G8,'Code Lists'!$G:$H,2,FALSE),"") -> BEG | I8: M,L | J8: 2026 | K8: Floral | L8: Collared | M8: Elegant beige button-down midi dress featuring peach floral motifs, subtle vertical stripe detailing, a classic shirt collar and 3/4 sleeves in a structured straight silhouette. | N8: Yes | O8: 2 | P8: 998822 | Q8: =IF(VedAarnaSKUMaster[[#This Row],[HSN/SAC Code]]=998822,5%,IF(VedAarnaSKUMaster[[#This Row],[HSN/SAC Code]]=998391,18%,IF(VedAarnaSKUMaster[[#This Row],[HSN/SAC Code]]=998723,5%,""))) -> 0.05 | R8: =IF(OR(A8="",C8="",H8="",J8=""),"","VS-"&C8&IF(D8<>"","-"&D8,"")&"-"&TEXT(A8,"0000")&"-"&H8&"-"&RIGHT(TEXT(J8,"0000"),2)) -> VS-OPC-1PC-0007-BEG-26 | S8: =IF(OR(A8="",C8="",F8="",H8="",I8="",J8=""),"","VS-"&C8&IF(D8<>"","-"&D8,"")&"-"&TEXT(A8,"0000")&"-"&F8&"-"&H8&"-"&I8&"-"&RIGHT(TEXT(J8,"0000"),2)) -> VS-OPC-1PC-0007-CHS-BEG-M,L-26 | T8: Beige Peach Floral Button-Down Midi Dress | U8: =IF(OR(VedAarnaSKUMaster[[#This Row],[Selling Price]]="",VedAarnaSKUMaster[[#This Row],[Selling Price]]=0),"",CEILING(VedAarnaSKUMaster[[#This Row],[Selling Price]]/(1-20%),100)-1) -> 3799 | V8: =ROUND(W8/(1-50%),-2) -> 3000 | W8: 1500 | X8: Complete | Y8: Live | Z8: =IF($R8="","",$R8&"-01-FR.png") -> VS-OPC-1PC-0007-BEG-26-01-FR.png | AA8: =IF($R8="","",$R8&"-02-SD.png") -> VS-OPC-1PC-0007-BEG-26-02-SD.png | AB8: =IF($R8="","",$R8&"-03-BK.png") -> VS-OPC-1PC-0007-BEG-26-03-BK.png | AC8: =IF($R8="","",$R8&"-04-CD.png") -> VS-OPC-1PC-0007-BEG-26-04-CD.png | AD8: =IF($R8="","",$R8&"-05-WK.png") -> VS-OPC-1PC-0007-BEG-26-05-WK.png | AE8: =IF($R8="","",$R8&"-06-ST.png") -> VS-OPC-1PC-0007-BEG-26-06-ST.png | AF8: =IF($R8="","",$R8&"-FB.png") -> VS-OPC-1PC-0007-BEG-26-FB.png | AG8: =IF($R8="","",$R8&"-DT.png") -> VS-OPC-1PC-0007-BEG-26-DT.png | AH8: =IF($R8="","",$R8&"-REF-01.png") -> VS-OPC-1PC-0007-BEG-26-REF-01.png
A9: 8 | B9: Suit Set | C9: =IFERROR(VLOOKUP(B9,'Code Lists'!$A:$B,2,FALSE),"") -> SUT | D9: 3PC | E9: Pure Cotton | F9: =IFERROR(VLOOKUP(E9,'Code Lists'!$D:$E,2,FALSE),"") -> PCT | G9: Aqua Green | H9: =IFERROR(VLOOKUP(G9,'Code Lists'!$G:$H,2,FALSE),"") -> AQG | I9: M,L,XL | J9: 2026 | K9: Leaf Print | L9: Round Neck | M9: Aqua green and beige leaf-print straight kurta paired with striped palazzo pants and a coordinated aqua printed dupatta. Features a round neck, 3/4 sleeves and contrasting border details. | N9: No | O9: 3 | P9: 998822 | Q9: =IF(VedAarnaSKUMaster[[#This Row],[HSN/SAC Code]]=998822,5%,IF(VedAarnaSKUMaster[[#This Row],[HSN/SAC Code]]=998391,18%,IF(VedAarnaSKUMaster[[#This Row],[HSN/SAC Code]]=998723,5%,""))) -> 0.05 | R9: =IF(OR(A9="",C9="",H9="",J9=""),"","VS-"&C9&IF(D9<>"","-"&D9,"")&"-"&TEXT(A9,"0000")&"-"&H9&"-"&RIGHT(TEXT(J9,"0000"),2)) -> VS-SUT-3PC-0008-AQG-26 | S9: =IF(OR(A9="",C9="",F9="",H9="",I9="",J9=""),"","VS-"&C9&IF(D9<>"","-"&D9,"")&"-"&TEXT(A9,"0000")&"-"&F9&"-"&H9&"-"&I9&"-"&RIGHT(TEXT(J9,"0000"),2)) -> VS-SUT-3PC-0008-PCT-AQG-M,L,XL-26 | T9: Aqua Beige Leaf Print Kurta Palazzo Set with Dupatta | U9: =IF(OR(VedAarnaSKUMaster[[#This Row],[Selling Price]]="",VedAarnaSKUMaster[[#This Row],[Selling Price]]=0),"",CEILING(VedAarnaSKUMaster[[#This Row],[Selling Price]]/(1-20%),100)-1) -> 3799 | V9: =ROUND(W9/(1-50%),-2) -> 3000 | W9: 1500 | X9: Complete | Y9: Live | Z9: =IF($R9="","",$R9&"-01-FR.png") -> VS-SUT-3PC-0008-AQG-26-01-FR.png | AA9: =IF($R9="","",$R9&"-02-SD.png") -> VS-SUT-3PC-0008-AQG-26-02-SD.png | AB9: =IF($R9="","",$R9&"-03-BK.png") -> VS-SUT-3PC-0008-AQG-26-03-BK.png | AC9: =IF($R9="","",$R9&"-04-CD.png") -> VS-SUT-3PC-0008-AQG-26-04-CD.png | AD9: =IF($R9="","",$R9&"-05-WK.png") -> VS-SUT-3PC-0008-AQG-26-05-WK.png | AE9: =IF($R9="","",$R9&"-06-ST.png") -> VS-SUT-3PC-0008-AQG-26-06-ST.png | AF9: =IF($R9="","",$R9&"-FB.png") -> VS-SUT-3PC-0008-AQG-26-FB.png | AG9: =IF($R9="","",$R9&"-DT.png") -> VS-SUT-3PC-0008-AQG-26-DT.png | AH9: =IF($R9="","",$R9&"-REF-01.png") -> VS-SUT-3PC-0008-AQG-26-REF-01.png
A10: 9 | B10: One Piece | C10: =IFERROR(VLOOKUP(B10,'Code Lists'!$A:$B,2,FALSE),"") -> OPC | D10: 1PC | E10: Velvet | F10: =IFERROR(VLOOKUP(E10,'Code Lists'!$D:$E,2,FALSE),"") -> VLT | G10: Burgundy | H10: =IFERROR(VLOOKUP(G10,'Code Lists'!$G:$H,2,FALSE),"") -> BGY | I10: M,L | J10: 2026 | K10: Floral | L10: Sweetheart | M10: Wine floral-print sleeveless short dress featuring a sweetheart neckline, broad shoulder straps, gathered waist and statement open-back tie-up bow. | N10: No | O10: 2 | P10: 998822 | Q10: =IF(VedAarnaSKUMaster[[#This Row],[HSN/SAC Code]]=998822,5%,IF(VedAarnaSKUMaster[[#This Row],[HSN/SAC Code]]=998391,18%,IF(VedAarnaSKUMaster[[#This Row],[HSN/SAC Code]]=998723,5%,""))) -> 0.05 | R10: =IF(OR(A10="",C10="",H10="",J10=""),"","VS-"&C10&IF(D10<>"","-"&D10,"")&"-"&TEXT(A10,"0000")&"-"&H10&"-"&RIGHT(TEXT(J10,"0000"),2)) -> VS-OPC-1PC-0009-BGY-26 | S10: =IF(OR(A10="",C10="",F10="",H10="",I10="",J10=""),"","VS-"&C10&IF(D10<>"","-"&D10,"")&"-"&TEXT(A10,"0000")&"-"&F10&"-"&H10&"-"&I10&"-"&RIGHT(TEXT(J10,"0000"),2)) -> VS-OPC-1PC-0009-VLT-BGY-M,L-26 | T10: Wine Floral Print Back-Tie Short Dress | U10: =IF(OR(VedAarnaSKUMaster[[#This Row],[Selling Price]]="",VedAarnaSKUMaster[[#This Row],[Selling Price]]=0),"",CEILING(VedAarnaSKUMaster[[#This Row],[Selling Price]]/(1-20%),100)-1) -> 2799 | V10: =ROUND(W10/(1-50%),-2) -> 2200 | W10: 1100 | X10: Complete | Y10: Live | Z10: =IF($R10="","",$R10&"-01-FR.png") -> VS-OPC-1PC-0009-BGY-26-01-FR.png | AA10: =IF($R10="","",$R10&"-02-SD.png") -> VS-OPC-1PC-0009-BGY-26-02-SD.png | AB10: =IF($R10="","",$R10&"-03-BK.png") -> VS-OPC-1PC-0009-BGY-26-03-BK.png | AC10: =IF($R10="","",$R10&"-04-CD.png") -> VS-OPC-1PC-0009-BGY-26-04-CD.png | AD10: =IF($R10="","",$R10&"-05-WK.png") -> VS-OPC-1PC-0009-BGY-26-05-WK.png | AE10: =IF($R10="","",$R10&"-06-ST.png") -> VS-OPC-1PC-0009-BGY-26-06-ST.png | AF10: =IF($R10="","",$R10&"-FB.png") -> VS-OPC-1PC-0009-BGY-26-FB.png | AG10: =IF($R10="","",$R10&"-DT.png") -> VS-OPC-1PC-0009-BGY-26-DT.png | AH10: =IF($R10="","",$R10&"-REF-01.png") -> VS-OPC-1PC-0009-BGY-26-REF-01.png
A11: 10 | B11: Suit Set | C11: =IFERROR(VLOOKUP(B11,'Code Lists'!$A:$B,2,FALSE),"") -> SUT | D11: 3PC | E11: Mix Cotton | F11: =IFERROR(VLOOKUP(E11,'Code Lists'!$D:$E,2,FALSE),"") -> MIC | G11: Mint | H11: =IFERROR(VLOOKUP(G11,'Code Lists'!$G:$H,2,FALSE),"") -> MNT | I11: M,L,XL | J11: 2026 | K11: Floral | L11: Round Neck | M11: Mint green 3-piece straight kurta set featuring an all-over delicate floral print, notched round neckline, scalloped sleeve detailing, straight pants and a coordinated embellished dupatta. | N11: No | O11: 3 | P11: 998822 | Q11: =IF(VedAarnaSKUMaster[[#This Row],[HSN/SAC Code]]=998822,5%,IF(VedAarnaSKUMaster[[#This Row],[HSN/SAC Code]]=998391,18%,IF(VedAarnaSKUMaster[[#This Row],[HSN/SAC Code]]=998723,5%,""))) -> 0.05 | R11: =IF(OR(A11="",C11="",H11="",J11=""),"","VS-"&C11&IF(D11<>"","-"&D11,"")&"-"&TEXT(A11,"0000")&"-"&H11&"-"&RIGHT(TEXT(J11,"0000"),2)) -> VS-SUT-3PC-0010-MNT-26 | S11: =IF(OR(A11="",C11="",F11="",H11="",I11="",J11=""),"","VS-"&C11&IF(D11<>"","-"&D11,"")&"-"&TEXT(A11,"0000")&"-"&F11&"-"&H11&"-"&I11&"-"&RIGHT(TEXT(J11,"0000"),2)) -> VS-SUT-3PC-0010-MIC-MNT-M,L,XL-26 | T11: Mint Green Floral Print Kurta Set with Dupatta | U11: =IF(OR(VedAarnaSKUMaster[[#This Row],[Selling Price]]="",VedAarnaSKUMaster[[#This Row],[Selling Price]]=0),"",CEILING(VedAarnaSKUMaster[[#This Row],[Selling Price]]/(1-20%),100)-1) -> 3499 | V11: =ROUND(W11/(1-50%),-2) -> 2800 | W11: 1400 | X11: Complete | Y11: Live | Z11: =IF($R11="","",$R11&"-01-FR.png") -> VS-SUT-3PC-0010-MNT-26-01-FR.png | AA11: =IF($R11="","",$R11&"-02-SD.png") -> VS-SUT-3PC-0010-MNT-26-02-SD.png | AB11: =IF($R11="","",$R11&"-03-BK.png") -> VS-SUT-3PC-0010-MNT-26-03-BK.png | AC11: =IF($R11="","",$R11&"-04-CD.png") -> VS-SUT-3PC-0010-MNT-26-04-CD.png | AD11: =IF($R11="","",$R11&"-05-WK.png") -> VS-SUT-3PC-0010-MNT-26-05-WK.png | AE11: =IF($R11="","",$R11&"-06-ST.png") -> VS-SUT-3PC-0010-MNT-26-06-ST.png | AF11: =IF($R11="","",$R11&"-FB.png") -> VS-SUT-3PC-0010-MNT-26-FB.png | AG11: =IF($R11="","",$R11&"-DT.png") -> VS-SUT-3PC-0010-MNT-26-DT.png | AH11: =IF($R11="","",$R11&"-REF-01.png") -> VS-SUT-3PC-0010-MNT-26-REF-01.png
A12: 11 | B12: One Piece | C12: =IFERROR(VLOOKUP(B12,'Code Lists'!$A:$B,2,FALSE),"") -> OPC | D12: 1PC | E12: Velvet | F12: =IFERROR(VLOOKUP(E12,'Code Lists'!$D:$E,2,FALSE),"") -> VLT | G12: Multicolor | H12: =IFERROR(VLOOKUP(G12,'Code Lists'!$G:$H,2,FALSE),"") -> MLT | I12: M,L | J12: 2026 | K12: Floral | L12: Round Neck | M12: Sleeveless multicolor floral velvet sheath dress with a dark base, round neckline, defined waist seam and fitted knee-length silhouette. | N12: No | O12: 2 | P12: 998822 | Q12: =IF(VedAarnaSKUMaster[[#This Row],[HSN/SAC Code]]=998822,5%,IF(VedAarnaSKUMaster[[#This Row],[HSN/SAC Code]]=998391,18%,IF(VedAarnaSKUMaster[[#This Row],[HSN/SAC Code]]=998723,5%,""))) -> 0.05 | R12: =IF(OR(A12="",C12="",H12="",J12=""),"","VS-"&C12&IF(D12<>"","-"&D12,"")&"-"&TEXT(A12,"0000")&"-"&H12&"-"&RIGHT(TEXT(J12,"0000"),2)) -> VS-OPC-1PC-0011-MLT-26 | S12: =IF(OR(A12="",C12="",F12="",H12="",I12="",J12=""),"","VS-"&C12&IF(D12<>"","-"&D12,"")&"-"&TEXT(A12,"0000")&"-"&F12&"-"&H12&"-"&I12&"-"&RIGHT(TEXT(J12,"0000"),2)) -> VS-OPC-1PC-0011-VLT-MLT-M,L-26 | T12: Multicolor Velvet Floral Sheath Dress | U12: =IF(OR(VedAarnaSKUMaster[[#This Row],[Selling Price]]="",VedAarnaSKUMaster[[#This Row],[Selling Price]]=0),"",CEILING(VedAarnaSKUMaster[[#This Row],[Selling Price]]/(1-20%),100)-1) -> 2899 | V12: =ROUND(W12/(1-50%),-2) -> 2300 | W12: 1150 | X12: Complete | Y12: Live | Z12: =IF($R12="","",$R12&"-01-FR.png") -> VS-OPC-1PC-0011-MLT-26-01-FR.png | AA12: =IF($R12="","",$R12&"-02-SD.png") -> VS-OPC-1PC-0011-MLT-26-02-SD.png | AB12: =IF($R12="","",$R12&"-03-BK.png") -> VS-OPC-1PC-0011-MLT-26-03-BK.png | AC12: =IF($R12="","",$R12&"-04-CD.png") -> VS-OPC-1PC-0011-MLT-26-04-CD.png | AD12: =IF($R12="","",$R12&"-05-WK.png") -> VS-OPC-1PC-0011-MLT-26-05-WK.png | AE12: =IF($R12="","",$R12&"-06-ST.png") -> VS-OPC-1PC-0011-MLT-26-06-ST.png | AF12: =IF($R12="","",$R12&"-FB.png") -> VS-OPC-1PC-0011-MLT-26-FB.png | AG12: =IF($R12="","",$R12&"-DT.png") -> VS-OPC-1PC-0011-MLT-26-DT.png | AH12: =IF($R12="","",$R12&"-REF-01.png") -> VS-OPC-1PC-0011-MLT-26-REF-01.png
A13: 12 | B13: Suit Set | C13: =IFERROR(VLOOKUP(B13,'Code Lists'!$A:$B,2,FALSE),"") -> SUT | D13: 2PC | E13: Cotton Doby | F13: =IFERROR(VLOOKUP(E13,'Code Lists'!$D:$E,2,FALSE),"") -> CTD | G13: Pale Yellow | H13: =IFERROR(VLOOKUP(G13,'Code Lists'!$G:$H,2,FALSE),"") -> PYL | I13: M,L,XL,2XL | J13: 2026 | K13: Embroidered | L13: V-Neck | M13: Mustard yellow 2-piece straight kurta set featuring delicate pink floral buti embroidery, V-neckline, statement pink embroidered cuffs and coordinated straight pants. | N13: Yes | O13: 4 | P13: 998822 | Q13: =IF(VedAarnaSKUMaster[[#This Row],[HSN/SAC Code]]=998822,5%,IF(VedAarnaSKUMaster[[#This Row],[HSN/SAC Code]]=998391,18%,IF(VedAarnaSKUMaster[[#This Row],[HSN/SAC Code]]=998723,5%,""))) -> 0.05 | R13: =IF(OR(A13="",C13="",H13="",J13=""),"","VS-"&C13&IF(D13<>"","-"&D13,"")&"-"&TEXT(A13,"0000")&"-"&H13&"-"&RIGHT(TEXT(J13,"0000"),2)) -> VS-SUT-2PC-0012-PYL-26 | S13: =IF(OR(A13="",C13="",F13="",H13="",I13="",J13=""),"","VS-"&C13&IF(D13<>"","-"&D13,"")&"-"&TEXT(A13,"0000")&"-"&F13&"-"&H13&"-"&I13&"-"&RIGHT(TEXT(J13,"0000"),2)) -> VS-SUT-2PC-0012-CTD-PYL-M,L,XL,2XL-26 | T13: Mustard Yellow Embroidered Kurta & Pant Set | U13: =IF(OR(VedAarnaSKUMaster[[#This Row],[Selling Price]]="",VedAarnaSKUMaster[[#This Row],[Selling Price]]=0),"",CEILING(VedAarnaSKUMaster[[#This Row],[Selling Price]]/(1-20%),100)-1) -> 1799 | V13: =ROUND(W13/(1-50%),-2) -> 1400 | W13: 700 | X13: Complete | Y13: Live | Z13: =IF($R13="","",$R13&"-01-FR.png") -> VS-SUT-2PC-0012-PYL-26-01-FR.png | AA13: =IF($R13="","",$R13&"-02-SD.png") -> VS-SUT-2PC-0012-PYL-26-02-SD.png | AB13: =IF($R13="","",$R13&"-03-BK.png") -> VS-SUT-2PC-0012-PYL-26-03-BK.png | AC13: =IF($R13="","",$R13&"-04-CD.png") -> VS-SUT-2PC-0012-PYL-26-04-CD.png | AD13: =IF($R13="","",$R13&"-05-WK.png") -> VS-SUT-2PC-0012-PYL-26-05-WK.png | AE13: =IF($R13="","",$R13&"-06-ST.png") -> VS-SUT-2PC-0012-PYL-26-06-ST.png | AF13: =IF($R13="","",$R13&"-FB.png") -> VS-SUT-2PC-0012-PYL-26-FB.png | AG13: =IF($R13="","",$R13&"-DT.png") -> VS-SUT-2PC-0012-PYL-26-DT.png | AH13: =IF($R13="","",$R13&"-REF-01.png") -> VS-SUT-2PC-0012-PYL-26-REF-01.png
... A35: 34 | B35: Shirt | C35: =IFERROR(VLOOKUP(B35,'Code Lists'!$A:$B,2,FALSE),"") -> SHT | D35: 1PC | E35: Cotton | F35: =IFERROR(VLOOKUP(E35,'Code Lists'!$D:$E,2,FALSE),"") -> CTN | G35: Mustard | H35: =IFERROR(VLOOKUP(G35,'Code Lists'!$G:$H,2,FALSE),"") -> MST | I35: M,L,XL,2XL | J35: 2026 | K35: Embroidered | L35: V-Neck | M35: Brighten everyday dressing with this mustard yellow embroidered top from VedAarna Studio. Designed with graceful coral-toned leaf-vine embroidery around the V-neckline, it features a contemporary band collar, comfortable three-quarter sleeves with broad cuffs and an easy regular silhouette. The softly curved hem completes the versatile design, making it an effortless pairing with denim, trousers or solid bottoms. | N35: No | O35: 4 | P35: 998822 | Q35: =IF(VedAarnaSKUMaster[[#This Row],[HSN/SAC Code]]=998822,5%,IF(VedAarnaSKUMaster[[#This Row],[HSN/SAC Code]]=998391,18%,IF(VedAarnaSKUMaster[[#This Row],[HSN/SAC Code]]=998723,5%,""))) -> 0.05 | R35: =IF(OR(A35="",C35="",H35="",J35=""),"","VS-"&C35&IF(D35<>"","-"&D35,"")&"-"&TEXT(A35,"0000")&"-"&H35&"-"&RIGHT(TEXT(J35,"0000"),2)) -> VS-SHT-1PC-0034-MST-26 | S35: =IF(OR(A35="",C35="",F35="",H35="",I35="",J35=""),"","VS-"&C35&IF(D35<>"","-"&D35,"")&"-"&TEXT(A35,"0000")&"-"&F35&"-"&H35&"-"&I35&"-"&RIGHT(TEXT(J35,"0000"),2)) -> VS-SHT-1PC-0034-CTN-MST-M,L,XL,2XL-26 | T35: VedAarna Women Mustard Yellow Leaf Embroidered V-Neck Three-Quarter Sleeve Top | U35: =IF(OR(VedAarnaSKUMaster[[#This Row],[Selling Price]]="",VedAarnaSKUMaster[[#This Row],[Selling Price]]=0),"",CEILING(VedAarnaSKUMaster[[#This Row],[Selling Price]]/(1-20%),100)-1) -> 999 | V35: =ROUND(W35/(1-50%),-2) -> 800 | W35: 420 | X35: Complete | Y35: Draft | Z35: =IF($R35="","",$R35&"-01-FR.png") -> VS-SHT-1PC-0034-MST-26-01-FR.png | AA35: =IF($R35="","",$R35&"-02-SD.png") -> VS-SHT-1PC-0034-MST-26-02-SD.png | AB35: =IF($R35="","",$R35&"-03-BK.png") -> VS-SHT-1PC-0034-MST-26-03-BK.png | AC35: =IF($R35="","",$R35&"-04-CD.png") -> VS-SHT-1PC-0034-MST-26-04-CD.png | AD35: =IF($R35="","",$R35&"-05-WK.png") -> VS-SHT-1PC-0034-MST-26-05-WK.png | AE35: =IF($R35="","",$R35&"-06-ST.png") -> VS-SHT-1PC-0034-MST-26-06-ST.png | AF35: =IF($R35="","",$R35&"-FB.png") -> VS-SHT-1PC-0034-MST-26-FB.png | AG35: =IF($R35="","",$R35&"-DT.png") -> VS-SHT-1PC-0034-MST-26-DT.png | AH35: =IF($R35="","",$R35&"-REF-01.png") -> VS-SHT-1PC-0034-MST-26-REF-01.png
C36: =IFERROR(VLOOKUP(B36,'Code Lists'!$A:$B,2,FALSE),"") | F36: =IFERROR(VLOOKUP(E36,'Code Lists'!$D:$E,2,FALSE),"") | H36: =IFERROR(VLOOKUP(G36,'Code Lists'!$G:$H,2,FALSE),"") | Q36: =IF(VedAarnaSKUMaster[[#This Row],[HSN/SAC Code]]=998822,5%,IF(VedAarnaSKUMaster[[#This Row],[HSN/SAC Code]]=998391,18%,IF(VedAarnaSKUMaster[[#This Row],[HSN/SAC Code]]=998723,5%,""))) | R36: =IF(OR(A36="",C36="",H36="",J36=""),"","VS-"&C36&IF(D36<>"","-"&D36,"")&"-"&TEXT(A36,"0000")&"-"&H36&"-"&RIGHT(TEXT(J36,"0000"),2)) | S36: =IF(OR(A36="",C36="",F36="",H36="",I36="",J36=""),"","VS-"&C36&IF(D36<>"","-"&D36,"")&"-"&TEXT(A36,"0000")&"-"&F36&"-"&H36&"-"&I36&"-"&RIGHT(TEXT(J36,"0000"),2)) | U36: =IF(OR(VedAarnaSKUMaster[[#This Row],[Selling Price]]="",VedAarnaSKUMaster[[#This Row],[Selling Price]]=0),"",CEILING(VedAarnaSKUMaster[[#This Row],[Selling Price]]/(1-20%),100)-1) | V36: =ROUND(W36/(1-50%),-2) -> 0 | Z36: =IF($R36="","",$R36&"-01-FR.png") | AA36: =IF($R36="","",$R36&"-02-SD.png") | AB36: =IF($R36="","",$R36&"-03-BK.png") | AC36: =IF($R36="","",$R36&"-04-CD.png") | AD36: =IF($R36="","",$R36&"-05-WK.png") | AE36: =IF($R36="","",$R36&"-06-ST.png") | AF36: =IF($R36="","",$R36&"-FB.png") | AG36: =IF($R36="","",$R36&"-DT.png") | AH36: =IF($R36="","",$R36&"-REF-01.png")
C37: =IFERROR(VLOOKUP(B37,'Code Lists'!$A:$B,2,FALSE),"") | F37: =IFERROR(VLOOKUP(E37,'Code Lists'!$D:$E,2,FALSE),"") | H37: =IFERROR(VLOOKUP(G37,'Code Lists'!$G:$H,2,FALSE),"") | Q37: =IF(VedAarnaSKUMaster[[#This Row],[HSN/SAC Code]]=998822,5%,IF(VedAarnaSKUMaster[[#This Row],[HSN/SAC Code]]=998391,18%,IF(VedAarnaSKUMaster[[#This Row],[HSN/SAC Code]]=998723,5%,""))) | R37: =IF(OR(A37="",C37="",H37="",J37=""),"","VS-"&C37&IF(D37<>"","-"&D37,"")&"-"&TEXT(A37,"0000")&"-"&H37&"-"&RIGHT(TEXT(J37,"0000"),2)) | S37: =IF(OR(A37="",C37="",F37="",H37="",I37="",J37=""),"","VS-"&C37&IF(D37<>"","-"&D37,"")&"-"&TEXT(A37,"0000")&"-"&F37&"-"&H37&"-"&I37&"-"&RIGHT(TEXT(J37,"0000"),2)) | U37: =IF(OR(VedAarnaSKUMaster[[#This Row],[Selling Price]]="",VedAarnaSKUMaster[[#This Row],[Selling Price]]=0),"",CEILING(VedAarnaSKUMaster[[#This Row],[Selling Price]]/(1-20%),100)-1) | V37: =ROUND(W37/(1-50%),-2) -> 0 | Z37: =IF($R37="","",$R37&"-01-FR.png") | AA37: =IF($R37="","",$R37&"-02-SD.png") | AB37: =IF($R37="","",$R37&"-03-BK.png") | AC37: =IF($R37="","",$R37&"-04-CD.png") | AD37: =IF($R37="","",$R37&"-05-WK.png") | AE37: =IF($R37="","",$R37&"-06-ST.png") | AF37: =IF($R37="","",$R37&"-FB.png") | AG37: =IF($R37="","",$R37&"-DT.png") | AH37: =IF($R37="","",$R37&"-REF-01.png")
C38: =IFERROR(VLOOKUP(B38,'Code Lists'!$A:$B,2,FALSE),"") | F38: =IFERROR(VLOOKUP(E38,'Code Lists'!$D:$E,2,FALSE),"") | H38: =IFERROR(VLOOKUP(G38,'Code Lists'!$G:$H,2,FALSE),"") | Q38: =IF(VedAarnaSKUMaster[[#This Row],[HSN/SAC Code]]=998822,5%,IF(VedAarnaSKUMaster[[#This Row],[HSN/SAC Code]]=998391,18%,IF(VedAarnaSKUMaster[[#This Row],[HSN/SAC Code]]=998723,5%,""))) | R38: =IF(OR(A38="",C38="",H38="",J38=""),"","VS-"&C38&IF(D38<>"","-"&D38,"")&"-"&TEXT(A38,"0000")&"-"&H38&"-"&RIGHT(TEXT(J38,"0000"),2)) | S38: =IF(OR(A38="",C38="",F38="",H38="",I38="",J38=""),"","VS-"&C38&IF(D38<>"","-"&D38,"")&"-"&TEXT(A38,"0000")&"-"&F38&"-"&H38&"-"&I38&"-"&RIGHT(TEXT(J38,"0000"),2)) | U38: =IF(OR(VedAarnaSKUMaster[[#This Row],[Selling Price]]="",VedAarnaSKUMaster[[#This Row],[Selling Price]]=0),"",CEILING(VedAarnaSKUMaster[[#This Row],[Selling Price]]/(1-20%),100)-1) | V38: =ROUND(W38/(1-50%),-2) -> 0 | Z38: =IF($R38="","",$R38&"-01-FR.png") | AA38: =IF($R38="","",$R38&"-02-SD.png") | AB38: =IF($R38="","",$R38&"-03-BK.png") | AC38: =IF($R38="","",$R38&"-04-CD.png") | AD38: =IF($R38="","",$R38&"-05-WK.png") | AE38: =IF($R38="","",$R38&"-06-ST.png") | AF38: =IF($R38="","",$R38&"-FB.png") | AG38: =IF($R38="","",$R38&"-DT.png") | AH38: =IF($R38="","",$R38&"-REF-01.png")
C39: =IFERROR(VLOOKUP(B39,'Code Lists'!$A:$B,2,FALSE),"") | F39: =IFERROR(VLOOKUP(E39,'Code Lists'!$D:$E,2,FALSE),"") | H39: =IFERROR(VLOOKUP(G39,'Code Lists'!$G:$H,2,FALSE),"") | Q39: =IF(VedAarnaSKUMaster[[#This Row],[HSN/SAC Code]]=998822,5%,IF(VedAarnaSKUMaster[[#This Row],[HSN/SAC Code]]=998391,18%,IF(VedAarnaSKUMaster[[#This Row],[HSN/SAC Code]]=998723,5%,""))) | R39: =IF(OR(A39="",C39="",H39="",J39=""),"","VS-"&C39&IF(D39<>"","-"&D39,"")&"-"&TEXT(A39,"0000")&"-"&H39&"-"&RIGHT(TEXT(J39,"0000"),2)) | S39: =IF(OR(A39="",C39="",F39="",H39="",I39="",J39=""),"","VS-"&C39&IF(D39<>"","-"&D39,"")&"-"&TEXT(A39,"0000")&"-"&F39&"-"&H39&"-"&I39&"-"&RIGHT(TEXT(J39,"0000"),2)) | U39: =IF(OR(VedAarnaSKUMaster[[#This Row],[Selling Price]]="",VedAarnaSKUMaster[[#This Row],[Selling Price]]=0),"",CEILING(VedAarnaSKUMaster[[#This Row],[Selling Price]]/(1-20%),100)-1) | V39: =ROUND(W39/(1-50%),-2) -> 0 | Z39: =IF($R39="","",$R39&"-01-FR.png") | AA39: =IF($R39="","",$R39&"-02-SD.png") | AB39: =IF($R39="","",$R39&"-03-BK.png") | AC39: =IF($R39="","",$R39&"-04-CD.png") | AD39: =IF($R39="","",$R39&"-05-WK.png") | AE39: =IF($R39="","",$R39&"-06-ST.png") | AF39: =IF($R39="","",$R39&"-FB.png") | AG39: =IF($R39="","",$R39&"-DT.png") | AH39: =IF($R39="","",$R39&"-REF-01.png")
C40: =IFERROR(VLOOKUP(B40,'Code Lists'!$A:$B,2,FALSE),"") | F40: =IFERROR(VLOOKUP(E40,'Code Lists'!$D:$E,2,FALSE),"") | H40: =IFERROR(VLOOKUP(G40,'Code Lists'!$G:$H,2,FALSE),"") | Q40: =IF(VedAarnaSKUMaster[[#This Row],[HSN/SAC Code]]=998822,5%,IF(VedAarnaSKUMaster[[#This Row],[HSN/SAC Code]]=998391,18%,IF(VedAarnaSKUMaster[[#This Row],[HSN/SAC Code]]=998723,5%,""))) | R40: =IF(OR(A40="",C40="",H40="",J40=""),"","VS-"&C40&IF(D40<>"","-"&D40,"")&"-"&TEXT(A40,"0000")&"-"&H40&"-"&RIGHT(TEXT(J40,"0000"),2)) | S40: =IF(OR(A40="",C40="",F40="",H40="",I40="",J40=""),"","VS-"&C40&IF(D40<>"","-"&D40,"")&"-"&TEXT(A40,"0000")&"-"&F40&"-"&H40&"-"&I40&"-"&RIGHT(TEXT(J40,"0000"),2)) | U40: =IF(OR(VedAarnaSKUMaster[[#This Row],[Selling Price]]="",VedAarnaSKUMaster[[#This Row],[Selling Price]]=0),"",CEILING(VedAarnaSKUMaster[[#This Row],[Selling Price]]/(1-20%),100)-1) | V40: =ROUND(W40/(1-50%),-2) -> 0 | Z40: =IF($R40="","",$R40&"-01-FR.png") | AA40: =IF($R40="","",$R40&"-02-SD.png") | AB40: =IF($R40="","",$R40&"-03-BK.png") | AC40: =IF($R40="","",$R40&"-04-CD.png") | AD40: =IF($R40="","",$R40&"-05-WK.png") | AE40: =IF($R40="","",$R40&"-06-ST.png") | AF40: =IF($R40="","",$R40&"-FB.png") | AG40: =IF($R40="","",$R40&"-DT.png") | AH40: =IF($R40="","",$R40&"-REF-01.png")
C41: =IFERROR(VLOOKUP(B41,'Code Lists'!$A:$B,2,FALSE),"") | F41: =IFERROR(VLOOKUP(E41,'Code Lists'!$D:$E,2,FALSE),"") | H41: =IFERROR(VLOOKUP(G41,'Code Lists'!$G:$H,2,FALSE),"") | Q41: =IF(VedAarnaSKUMaster[[#This Row],[HSN/SAC Code]]=998822,5%,IF(VedAarnaSKUMaster[[#This Row],[HSN/SAC Code]]=998391,18%,IF(VedAarnaSKUMaster[[#This Row],[HSN/SAC Code]]=998723,5%,""))) | R41: =IF(OR(A41="",C41="",H41="",J41=""),"","VS-"&C41&IF(D41<>"","-"&D41,"")&"-"&TEXT(A41,"0000")&"-"&H41&"-"&RIGHT(TEXT(J41,"0000"),2)) | S41: =IF(OR(A41="",C41="",F41="",H41="",I41="",J41=""),"","VS-"&C41&IF(D41<>"","-"&D41,"")&"-"&TEXT(A41,"0000")&"-"&F41&"-"&H41&"-"&I41&"-"&RIGHT(TEXT(J41,"0000"),2)) | U41: =IF(OR(VedAarnaSKUMaster[[#This Row],[Selling Price]]="",VedAarnaSKUMaster[[#This Row],[Selling Price]]=0),"",CEILING(VedAarnaSKUMaster[[#This Row],[Selling Price]]/(1-20%),100)-1) | V41: =ROUND(W41/(1-50%),-2) -> 0 | Z41: =IF($R41="","",$R41&"-01-FR.png") | AA41: =IF($R41="","",$R41&"-02-SD.png") | AB41: =IF($R41="","",$R41&"-03-BK.png") | AC41: =IF($R41="","",$R41&"-04-CD.png") | AD41: =IF($R41="","",$R41&"-05-WK.png") | AE41: =IF($R41="","",$R41&"-06-ST.png") | AF41: =IF($R41="","",$R41&"-FB.png") | AG41: =IF($R41="","",$R41&"-DT.png") | AH41: =IF($R41="","",$R41&"-REF-01.png")
C42: =IFERROR(VLOOKUP(B42,'Code Lists'!$A:$B,2,FALSE),"") | F42: =IFERROR(VLOOKUP(E42,'Code Lists'!$D:$E,2,FALSE),"") | H42: =IFERROR(VLOOKUP(G42,'Code Lists'!$G:$H,2,FALSE),"") | Q42: =IF(VedAarnaSKUMaster[[#This Row],[HSN/SAC Code]]=998822,5%,IF(VedAarnaSKUMaster[[#This Row],[HSN/SAC Code]]=998391,18%,IF(VedAarnaSKUMaster[[#This Row],[HSN/SAC Code]]=998723,5%,""))) | R42: =IF(OR(A42="",C42="",H42="",J42=""),"","VS-"&C42&IF(D42<>"","-"&D42,"")&"-"&TEXT(A42,"0000")&"-"&H42&"-"&RIGHT(TEXT(J42,"0000"),2)) | S42: =IF(OR(A42="",C42="",F42="",H42="",I42="",J42=""),"","VS-"&C42&IF(D42<>"","-"&D42,"")&"-"&TEXT(A42,"0000")&"-"&F42&"-"&H42&"-"&I42&"-"&RIGHT(TEXT(J42,"0000"),2)) | U42: =IF(OR(VedAarnaSKUMaster[[#This Row],[Selling Price]]="",VedAarnaSKUMaster[[#This Row],[Selling Price]]=0),"",CEILING(VedAarnaSKUMaster[[#This Row],[Selling Price]]/(1-20%),100)-1) | V42: =ROUND(W42/(1-50%),-2) -> 0 | Z42: =IF($R42="","",$R42&"-01-FR.png") | AA42: =IF($R42="","",$R42&"-02-SD.png") | AB42: =IF($R42="","",$R42&"-03-BK.png") | AC42: =IF($R42="","",$R42&"-04-CD.png") | AD42: =IF($R42="","",$R42&"-05-WK.png") | AE42: =IF($R42="","",$R42&"-06-ST.png") | AF42: =IF($R42="","",$R42&"-FB.png") | AG42: =IF($R42="","",$R42&"-DT.png") | AH42: =IF($R42="","",$R42&"-REF-01.png")
C43: =IFERROR(VLOOKUP(B43,'Code Lists'!$A:$B,2,FALSE),"") | F43: =IFERROR(VLOOKUP(E43,'Code Lists'!$D:$E,2,FALSE),"") | H43: =IFERROR(VLOOKUP(G43,'Code Lists'!$G:$H,2,FALSE),"") | Q43: =IF(VedAarnaSKUMaster[[#This Row],[HSN/SAC Code]]=998822,5%,IF(VedAarnaSKUMaster[[#This Row],[HSN/SAC Code]]=998391,18%,IF(VedAarnaSKUMaster[[#This Row],[HSN/SAC Code]]=998723,5%,""))) | R43: =IF(OR(A43="",C43="",H43="",J43=""),"","VS-"&C43&IF(D43<>"","-"&D43,"")&"-"&TEXT(A43,"0000")&"-"&H43&"-"&RIGHT(TEXT(J43,"0000"),2)) | S43: =IF(OR(A43="",C43="",F43="",H43="",I43="",J43=""),"","VS-"&C43&IF(D43<>"","-"&D43,"")&"-"&TEXT(A43,"0000")&"-"&F43&"-"&H43&"-"&I43&"-"&RIGHT(TEXT(J43,"0000"),2)) | U43: =IF(OR(VedAarnaSKUMaster[[#This Row],[Selling Price]]="",VedAarnaSKUMaster[[#This Row],[Selling Price]]=0),"",CEILING(VedAarnaSKUMaster[[#This Row],[Selling Price]]/(1-20%),100)-1) | V43: =ROUND(W43/(1-50%),-2) -> 0 | Z43: =IF($R43="","",$R43&"-01-FR.png") | AA43: =IF($R43="","",$R43&"-02-SD.png") | AB43: =IF($R43="","",$R43&"-03-BK.png") | AC43: =IF($R43="","",$R43&"-04-CD.png") | AD43: =IF($R43="","",$R43&"-05-WK.png") | AE43: =IF($R43="","",$R43&"-06-ST.png") | AF43: =IF($R43="","",$R43&"-FB.png") | AG43: =IF($R43="","",$R43&"-DT.png") | AH43: =IF($R43="","",$R43&"-REF-01.png")
C44: =IFERROR(VLOOKUP(B44,'Code Lists'!$A:$B,2,FALSE),"") | F44: =IFERROR(VLOOKUP(E44,'Code Lists'!$D:$E,2,FALSE),"") | H44: =IFERROR(VLOOKUP(G44,'Code Lists'!$G:$H,2,FALSE),"") | Q44: =IF(VedAarnaSKUMaster[[#This Row],[HSN/SAC Code]]=998822,5%,IF(VedAarnaSKUMaster[[#This Row],[HSN/SAC Code]]=998391,18%,IF(VedAarnaSKUMaster[[#This Row],[HSN/SAC Code]]=998723,5%,""))) | R44: =IF(OR(A44="",C44="",H44="",J44=""),"","VS-"&C44&IF(D44<>"","-"&D44,"")&"-"&TEXT(A44,"0000")&"-"&H44&"-"&RIGHT(TEXT(J44,"0000"),2)) | S44: =IF(OR(A44="",C44="",F44="",H44="",I44="",J44=""),"","VS-"&C44&IF(D44<>"","-"&D44,"")&"-"&TEXT(A44,"0000")&"-"&F44&"-"&H44&"-"&I44&"-"&RIGHT(TEXT(J44,"0000"),2)) | U44: =IF(OR(VedAarnaSKUMaster[[#This Row],[Selling Price]]="",VedAarnaSKUMaster[[#This Row],[Selling Price]]=0),"",CEILING(VedAarnaSKUMaster[[#This Row],[Selling Price]]/(1-20%),100)-1) | V44: =ROUND(W44/(1-50%),-2) -> 0 | Z44: =IF($R44="","",$R44&"-01-FR.png") | AA44: =IF($R44="","",$R44&"-02-SD.png") | AB44: =IF($R44="","",$R44&"-03-BK.png") | AC44: =IF($R44="","",$R44&"-04-CD.png") | AD44: =IF($R44="","",$R44&"-05-WK.png") | AE44: =IF($R44="","",$R44&"-06-ST.png") | AF44: =IF($R44="","",$R44&"-FB.png") | AG44: =IF($R44="","",$R44&"-DT.png") | AH44: =IF($R44="","",$R44&"-REF-01.png")
C45: =IFERROR(VLOOKUP(B45,'Code Lists'!$A:$B,2,FALSE),"") | F45: =IFERROR(VLOOKUP(E45,'Code Lists'!$D:$E,2,FALSE),"") | H45: =IFERROR(VLOOKUP(G45,'Code Lists'!$G:$H,2,FALSE),"") | Q45: =IF(VedAarnaSKUMaster[[#This Row],[HSN/SAC Code]]=998822,5%,IF(VedAarnaSKUMaster[[#This Row],[HSN/SAC Code]]=998391,18%,IF(VedAarnaSKUMaster[[#This Row],[HSN/SAC Code]]=998723,5%,""))) | R45: =IF(OR(A45="",C45="",H45="",J45=""),"","VS-"&C45&IF(D45<>"","-"&D45,"")&"-"&TEXT(A45,"0000")&"-"&H45&"-"&RIGHT(TEXT(J45,"0000"),2)) | S45: =IF(OR(A45="",C45="",F45="",H45="",I45="",J45=""),"","VS-"&C45&IF(D45<>"","-"&D45,"")&"-"&TEXT(A45,"0000")&"-"&F45&"-"&H45&"-"&I45&"-"&RIGHT(TEXT(J45,"0000"),2)) | U45: =IF(OR(VedAarnaSKUMaster[[#This Row],[Selling Price]]="",VedAarnaSKUMaster[[#This Row],[Selling Price]]=0),"",CEILING(VedAarnaSKUMaster[[#This Row],[Selling Price]]/(1-20%),100)-1) | V45: =ROUND(W45/(1-50%),-2) -> 0 | Z45: =IF($R45="","",$R45&"-01-FR.png") | AA45: =IF($R45="","",$R45&"-02-SD.png") | AB45: =IF($R45="","",$R45&"-03-BK.png") | AC45: =IF($R45="","",$R45&"-04-CD.png") | AD45: =IF($R45="","",$R45&"-05-WK.png") | AE45: =IF($R45="","",$R45&"-06-ST.png") | AF45: =IF($R45="","",$R45&"-FB.png") | AG45: =IF($R45="","",$R45&"-DT.png") | AH45: =IF($R45="","",$R45&"-REF-01.png")
C46: =IFERROR(VLOOKUP(B46,'Code Lists'!$A:$B,2,FALSE),"") | F46: =IFERROR(VLOOKUP(E46,'Code Lists'!$D:$E,2,FALSE),"") | H46: =IFERROR(VLOOKUP(G46,'Code Lists'!$G:$H,2,FALSE),"") | Q46: =IF(VedAarnaSKUMaster[[#This Row],[HSN/SAC Code]]=998822,5%,IF(VedAarnaSKUMaster[[#This Row],[HSN/SAC Code]]=998391,18%,IF(VedAarnaSKUMaster[[#This Row],[HSN/SAC Code]]=998723,5%,""))) | R46: =IF(OR(A46="",C46="",H46="",J46=""),"","VS-"&C46&IF(D46<>"","-"&D46,"")&"-"&TEXT(A46,"0000")&"-"&H46&"-"&RIGHT(TEXT(J46,"0000"),2)) | S46: =IF(OR(A46="",C46="",F46="",H46="",I46="",J46=""),"","VS-"&C46&IF(D46<>"","-"&D46,"")&"-"&TEXT(A46,"0000")&"-"&F46&"-"&H46&"-"&I46&"-"&RIGHT(TEXT(J46,"0000"),2)) | U46: =IF(OR(VedAarnaSKUMaster[[#This Row],[Selling Price]]="",VedAarnaSKUMaster[[#This Row],[Selling Price]]=0),"",CEILING(VedAarnaSKUMaster[[#This Row],[Selling Price]]/(1-20%),100)-1) | V46: =ROUND(W46/(1-50%),-2) -> 0 | Z46: =IF($R46="","",$R46&"-01-FR.png") | AA46: =IF($R46="","",$R46&"-02-SD.png") | AB46: =IF($R46="","",$R46&"-03-BK.png") | AC46: =IF($R46="","",$R46&"-04-CD.png") | AD46: =IF($R46="","",$R46&"-05-WK.png") | AE46: =IF($R46="","",$R46&"-06-ST.png") | AF46: =IF($R46="","",$R46&"-FB.png") | AG46: =IF($R46="","",$R46&"-DT.png") | AH46: =IF($R46="","",$R46&"-REF-01.png")
C47: =IFERROR(VLOOKUP(B47,'Code Lists'!$A:$B,2,FALSE),"") | F47: =IFERROR(VLOOKUP(E47,'Code Lists'!$D:$E,2,FALSE),"") | H47: =IFERROR(VLOOKUP(G47,'Code Lists'!$G:$H,2,FALSE),"") | Q47: =IF(VedAarnaSKUMaster[[#This Row],[HSN/SAC Code]]=998822,5%,IF(VedAarnaSKUMaster[[#This Row],[HSN/SAC Code]]=998391,18%,IF(VedAarnaSKUMaster[[#This Row],[HSN/SAC Code]]=998723,5%,""))) | R47: =IF(OR(A47="",C47="",H47="",J47=""),"","VS-"&C47&IF(D47<>"","-"&D47,"")&"-"&TEXT(A47,"0000")&"-"&H47&"-"&RIGHT(TEXT(J47,"0000"),2)) | S47: =IF(OR(A47="",C47="",F47="",H47="",I47="",J47=""),"","VS-"&C47&IF(D47<>"","-"&D47,"")&"-"&TEXT(A47,"0000")&"-"&F47&"-"&H47&"-"&I47&"-"&RIGHT(TEXT(J47,"0000"),2)) | U47: =IF(OR(VedAarnaSKUMaster[[#This Row],[Selling Price]]="",VedAarnaSKUMaster[[#This Row],[Selling Price]]=0),"",CEILING(VedAarnaSKUMaster[[#This Row],[Selling Price]]/(1-20%),100)-1) | V47: =ROUND(W47/(1-50%),-2) -> 0 | Z47: =IF($R47="","",$R47&"-01-FR.png") | AA47: =IF($R47="","",$R47&"-02-SD.png") | AB47: =IF($R47="","",$R47&"-03-BK.png") | AC47: =IF($R47="","",$R47&"-04-CD.png") | AD47: =IF($R47="","",$R47&"-05-WK.png") | AE47: =IF($R47="","",$R47&"-06-ST.png") | AF47: =IF($R47="","",$R47&"-FB.png") | AG47: =IF($R47="","",$R47&"-DT.png") | AH47: =IF($R47="","",$R47&"-REF-01.png")
... C500: =IFERROR(VLOOKUP(B500,'Code Lists'!$A:$B,2,FALSE),"") | F500: =IFERROR(VLOOKUP(E500,'Code Lists'!$D:$E,2,FALSE),"") | H500: =IFERROR(VLOOKUP(G500,'Code Lists'!$G:$H,2,FALSE),"") | Q500: =IF(VedAarnaSKUMaster[[#This Row],[HSN/SAC Code]]=998822,5%,IF(VedAarnaSKUMaster[[#This Row],[HSN/SAC Code]]=998391,18%,IF(VedAarnaSKUMaster[[#This Row],[HSN/SAC Code]]=998723,5%,""))) | R500: =IF(OR(A500="",C500="",H500="",J500=""),"","VS-"&C500&IF(D500<>"","-"&D500,"")&"-"&TEXT(A500,"0000")&"-"&H500&"-"&RIGHT(TEXT(J500,"0000"),2)) | S500: =IF(OR(A500="",C500="",F500="",H500="",I500="",J500=""),"","VS-"&C500&IF(D500<>"","-"&D500,"")&"-"&TEXT(A500,"0000")&"-"&F500&"-"&H500&"-"&I500&"-"&RIGHT(TEXT(J500,"0000"),2)) | U500: =IF(OR(VedAarnaSKUMaster[[#This Row],[Selling Price]]="",VedAarnaSKUMaster[[#This Row],[Selling Price]]=0),"",CEILING(VedAarnaSKUMaster[[#This Row],[Selling Price]]/(1-20%),100)-1) | V500: =ROUND(W500/(1-50%),-2) -> 0 | Z500: =IF($R500="","",$R500&"-01-FR.png") | AA500: =IF($R500="","",$R500&"-02-SD.png") | AB500: =IF($R500="","",$R500&"-03-BK.png") | AC500: =IF($R500="","",$R500&"-04-CD.png") | AD500: =IF($R500="","",$R500&"-05-WK.png") | AE500: =IF($R500="","",$R500&"-06-ST.png") | AF500: =IF($R500="","",$R500&"-FB.png") | AG500: =IF($R500="","",$R500&"-DT.png") | AH500: =IF($R500="","",$R500&"-REF-01.png")

Sheet Code Lists
A1: Garment Type | B1: Code | D1: Fabric | E1: Code | G1: Color | H1: Code | J1: Size | L1: Set Type | N1: Pattern | P1: Neck Type | R1: Pocket | T1: Photoshoot Status | V1: Website Status | X1: HSN/SAC Code | Y1: Service / Use | Z1: GST %
A2: Kurti | B2: KRT | D2: Cotton | E2: CTN | G2: Black | H2: BLK | J2: XXS | L2: 1PC | N2: Plain | P2: Round Neck | R2: Yes | T2: Pending | V2: Draft | X2: 998822 | Y2: Wearing apparel / manufacturing services | Z2: 0.05
A3: Kurti Set | B3: KRS | D3: Pure Cotton | E3: PCT | G3: White | H3: WHT | J3: XS | L3: 2PC | N3: Printed | P3: V-Neck | R3: No | T3: In Progress | V3: Ready | X3: 998391 | Y3: Luxury / Specialty Design | Z3: 0.18
A4: Suit Set | B4: SUT | D4: Mix Cotton | E4: MIC | G4: Ivory | H4: IVR | J4: S | L4: 3PC | N4: Embroidered | P4: U-Neck | T4: Complete | V4: Live | X4: 998723 | Y4: Alteration / Repair services | Z4: 0.05
A5: Anarkali | B5: ANK | D5: Cotton Doby | E5: CTD | G5: Beige | H5: BEG | J5: M | L5: 4PC | N5: Embellished | P5: Boat Neck | V5: Archived
A6: Dress | B6: DRS | D6: Jeera Doby | E6: JRD | G6: Cream | H6: CRM | J6: L | N6: Woven | P6: Square Neck
A7: Gown | B7: GWN | D7: Rubia Cotton | E7: RCT | G7: Red | H7: RED | J7: XL | N7: Jacquard | P7: Keyhole Neck
A8: Blouse | B8: BLS | D8: Linen | E8: LIN | G8: Maroon | H8: MRN | J8: XXL | N8: Floral | P8: Collared
A9: Lehenga | B9: LHN | D9: Rayon | E9: RYN | G9: Wine | H9: WIN | J9: 3XL | N9: Geometric | P9: Mandarin Collar
A10: Saree | B10: SAR | D10: Viscose | E10: VIS | G10: Pink | H10: PNK | J10: 4XL | N10: Striped | P10: Sweetheart
A11: Co-ord Set | B11: CRD | D11: Chanderi | E11: CHD | G11: Rose Pink | H11: RPK | J11: 5XL | N11: Checked | P11: Halter Neck
A12: Top | B12: TOP | D12: Chanderi Silk | E12: CHS | G12: Blush Pink | H12: BPK | J12: 6XL | N12: Solid | P12: High Neck
A13: Tunic | B13: TUN | D13: Organza | E13: ORG | G13: Rani Pink | H13: RNP | J13: FS | N13: Sequined | P13: Scoop Neck
A14: Shirt | B14: SHT | D14: Georgette | E14: GGT | G14: Fuchsia Pink | H14: FUS | J14: CUS | N14: Handwork | P14: Other
A15: Skirt | B15: SKT | D15: Chiffon | E15: CHF | G15: Magenta | H15: MAG | J15: S,M | N15: Bandhani
A16: Palazzo | B16: PLZ | D16: Crepe | E16: CRP | G16: Peach | H16: PCH | J16: M,L | N16: Solid with Embroidered Motifs
A17: Pants/Trouser | B17: PNT | D17: Silk | E17: SLK | G17: Orange | H17: ORN | J17: S,M,L | N17: Textured
A18: Sharara Set | B18: SHR | D18: Raw Silk | E18: RSL | G18: Rust | H18: RST | J18: M,L,XL | N18: Ethnic Motifs
A19: Salwar Set | B19: SLW | D19: Cotton Silk | E19: CSL | G19: Yellow | H19: YLW | J19: L,XL,2XL | N19: Paisley / Ethnic Print
A20: Kaftan | B20: KFT | D20: Art Silk | E20: ASL | G20: Pale Yellow | H20: PYL | J20: M,L,XL,2XL | N20: Leaf Print
A21: Jacket Set | B21: JKT | D21: Muslin | E21: MSL | G21: Mustard | H21: MST | J21: M,L,XL,2XL, 3XL, 4XL | N21: Other
A22: Indo-Western | B22: IDW | D22: Velvet | E22: VLT | G22: Green | H22: GRN | J22: S,M,L,XL
A23: Kids Wear | B23: KID | D23: Satin | E23: STN | G23: Olive | H23: OLV | J23: S,M,L,XL,XXL
A24: One Piece | B24: OPC | D24: Modal | E24: MDL | G24: Mint | H24: MNT
A25: Three Piece Set | B25: THS | D25: Khadi | E25: KHD | G25: Teal | H25: TEL
A26: Custom Design | B26: CUS | D26: Denim | E26: DNM | G26: Blue | H26: BLU
D27: Brocade | E27: BRC | G27: Navy Blue | H27: NVY
D28: Net | E28: NET | G28: Sky Blue | H28: SKY
D29: Tissue | E29: TIS | G29: Royal Blue | H29: RYB
D30: Kota Doria | E30: KTD | G30: Purple | H30: PPL
D31: Jacquard | E31: JQD | G31: Lavender | H31: LAV
D32: Mulmul Cotton | E32: MCT | G32: Grey | H32: GRY
D33: Shantoon | E33: SNT | G33: Brown | H33: BRN
G34: Gold | H34: GLD
G35: Silver | H35: SLV
G36: Deep Wine | H36: DPW
G37: Aqua Green | H37: AQG
G38: Burgundy | H38: BGY
G39: Multicolor | H39: MLT

Sheet Instructions
A1: VedAarna Studio — SKU, Product & Photoshoot Master Standard
A3: Item | B3: Standard | D3: HSN/SAC | E3: Description | F3: GST
A4: Brand Prefix | B4: VS | D4: 998822 | E4: Wearing apparel / manufacturing services | F4: 5%
A5: Design Number | B5: 4 digits: 0001–9999; globally unique | D5: 998391 | E5: Luxury / Specialty Design | F5: 18%
A6: Set Type | B6: 1PC / 2PC / 3PC / 4PC | D6: 998723 | E6: Alteration / Repair services | F6: 5%
A7: Model Number | B7: VS-[TYPE]-[SET]-[DESIGN]-[COLOR]-[YY] | D7: Note | E7: Verify tax classification/rate with your CA/GST adviser before invoicing.
A8: Example Model | B8: VS-SUT-3PC-0027-RST-26
A9: Sellable SKU | B9: VS-[TYPE]-[SET]-[DESIGN]-[FABRIC]-[COLOR]-[SIZE]-[YY]
A10: Example SKU | B10: VS-SUT-3PC-0027-CHD-RST-M-26
A11: GST | B11: Auto-populated from selected HSN/SAC code
A12: Year Rule | B12: Year the design was introduced
A14: How to use
A15: Enter Design No.; select Garment Type, Set Type, Fabric, Color, Size, Pattern, Neck Type, Pocket, HSN/SAC and statuses from dropdowns. Enter the short product description and stock quantity. Codes, GST %, Model Number, Sellable SKU and photo filenames generate automatically.
A16: Leave Set Type blank when it is not relevant to the product.
